devices_format/__init__.py
devices_format/main.py
device_format-0.1.1.dist-info/METADATA
device_format-0.1.1.dist-info/WHEEL
device_format-0.1.1.dist-info/top_level.txt
device_format-0.1.1.dist-info/RECORD
