Metadata-Version: 2.1
Name: device-format
Version: 0.1.1
Summary: This package is designed to generate regular expression formats based on device names.
Author: Aung Htoo Khine
